setup.cfg
setup.py
PureCloudPlatformApiSdk/__init__.py
PureCloudPlatformApiSdk/api_client.py
PureCloudPlatformApiSdk/configuration.py
PureCloudPlatformApiSdk/rest.py
PureCloudPlatformApiSdk.egg-info/PKG-INFO
PureCloudPlatformApiSdk.egg-info/SOURCES.txt
PureCloudPlatformApiSdk.egg-info/dependency_links.txt
PureCloudPlatformApiSdk.egg-info/requires.txt
PureCloudPlatformApiSdk.egg-info/top_level.txt
PureCloudPlatformApiSdk/apis/__init__.py
PureCloudPlatformApiSdk/apis/alerting_api.py
PureCloudPlatformApiSdk/apis/analytics_api.py
PureCloudPlatformApiSdk/apis/architect_api.py
PureCloudPlatformApiSdk/apis/attributes_api.py
PureCloudPlatformApiSdk/apis/authorization_api.py
PureCloudPlatformApiSdk/apis/content_management_api.py
PureCloudPlatformApiSdk/apis/conversations_api.py
PureCloudPlatformApiSdk/apis/external_contacts_api.py
PureCloudPlatformApiSdk/apis/fax_api.py
PureCloudPlatformApiSdk/apis/geolocation_api.py
PureCloudPlatformApiSdk/apis/greetings_api.py
PureCloudPlatformApiSdk/apis/groups_api.py
PureCloudPlatformApiSdk/apis/identity_provider_api.py
PureCloudPlatformApiSdk/apis/languages_api.py
PureCloudPlatformApiSdk/apis/locations_api.py
PureCloudPlatformApiSdk/apis/notifications_api.py
PureCloudPlatformApiSdk/apis/o_auth_api.py
PureCloudPlatformApiSdk/apis/organization_api.py
PureCloudPlatformApiSdk/apis/outbound_api.py
PureCloudPlatformApiSdk/apis/presence_api.py
PureCloudPlatformApiSdk/apis/quality_api.py
PureCloudPlatformApiSdk/apis/recording_api.py
PureCloudPlatformApiSdk/apis/response_management_api.py
PureCloudPlatformApiSdk/apis/routing_api.py
PureCloudPlatformApiSdk/apis/scripts_api.py
PureCloudPlatformApiSdk/apis/search_api.py
PureCloudPlatformApiSdk/apis/stations_api.py
PureCloudPlatformApiSdk/apis/suggest_api.py
PureCloudPlatformApiSdk/apis/telephony_providers_edge_api.py
PureCloudPlatformApiSdk/apis/tokens_api.py
PureCloudPlatformApiSdk/apis/user_recordings_api.py
PureCloudPlatformApiSdk/apis/users_api.py
PureCloudPlatformApiSdk/apis/utilities_api.py
PureCloudPlatformApiSdk/apis/voicemail_api.py
PureCloudPlatformApiSdk/apis/workforce_management_api.py
PureCloudPlatformApiSdk/models/__init__.py
PureCloudPlatformApiSdk/models/actions.py
