Metadata-Version: 1.0
Name: PureCloudPlatformApiSdk
Version: 0.45.1.101
Summary: PureCloud Platform API SDK
Home-page: https://developer.mypurecloud.com/api/rest/client-libraries/python/latest/
Author: Interactive Intelligence, Inc.
Author-email: DeveloperEvangelists@inin.com
License: UNKNOWN
Keywords: Swagger PureCloud Platform API ININ Interactive Intelligence
Platform: UNKNOWN
